slideflow_noncommercial/__init__.py
slideflow_noncommercial/_version.py
slideflow_noncommercial/biscuit/__init__.py
slideflow_noncommercial/biscuit/delong.py
slideflow_noncommercial/biscuit/errors.py
slideflow_noncommercial/biscuit/experiment.py
slideflow_noncommercial/biscuit/hp.py
slideflow_noncommercial/biscuit/threshold.py
slideflow_noncommercial/biscuit/utils.py
slideflow_noncommercial/extractors/__init__.py
slideflow_noncommercial/extractors/gigapath.py
slideflow_noncommercial/extractors/plip.py
slideflow_noncommercial/extractors/uni.py
slideflow_noncommercial/extractors/histossl/__init__.py
slideflow_noncommercial/extractors/histossl/_weight_init.py
slideflow_noncommercial/extractors/histossl/core.py
slideflow_noncommercial/extractors/histossl/encoders.py
slideflow_noncommercial/extractors/histossl/ibotvit.py
slideflow_noncommercial/extractors/histossl/utils.py
slideflow_noncommercial/extractors/phikon/__init__.py
slideflow_noncommercial/extractors/phikon/_weight_init.py
slideflow_noncommercial/extractors/phikon/core.py
slideflow_noncommercial/extractors/phikon/encoders.py
slideflow_noncommercial/extractors/phikon/ibotvit.py
slideflow_noncommercial/extractors/phikon/utils.py
slideflow_noncommercial/stylegan2/__init__.py
slideflow_noncommercial/stylegan2/calc_metrics.py
slideflow_noncommercial/stylegan2/dataset_tool.py
slideflow_noncommercial/stylegan2/generate.py
slideflow_noncommercial/stylegan2/generate_tfrecords.py
slideflow_noncommercial/stylegan2/interpolate.py
slideflow_noncommercial/stylegan2/projector.py
slideflow_noncommercial/stylegan2/style_mixing.py
slideflow_noncommercial/stylegan2/train.py
slideflow_noncommercial/stylegan2/stylegan2/__init__.py
slideflow_noncommercial/stylegan2/stylegan2/generate.py
slideflow_noncommercial/stylegan2/stylegan2/legacy.py
slideflow_noncommercial/stylegan2/stylegan2/train.py
slideflow_noncommercial/stylegan2/stylegan2/utils.py
slideflow_noncommercial/stylegan2/stylegan2/dnnlib/__init__.py
slideflow_noncommercial-0.0.2.dist-info/LICENSE
slideflow_noncommercial-0.0.2.dist-info/METADATA
slideflow_noncommercial-0.0.2.dist-info/WHEEL
slideflow_noncommercial-0.0.2.dist-info/entry_points.txt
slideflow_noncommercial-0.0.2.dist-info/top_level.txt
slideflow_noncommercial-0.0.2.dist-info/RECORD
