Metadata-Version: 2.1
Name: slideflow-noncommercial
Version: 0.0.2
Summary: Non-commercial extensions and tools for Slideflow.
Home-page: https://github.com/slideflow/slideflow-noncommercial
Author: James Dolezal
Author-email: james@slideflow.ai
License: Creative Commons Attribution-NonCommercial 4.0 International (CC BY-NC 4.0)
Classifier: Programming Language :: Python :: 3
Classifier: License :: Other/Proprietary License
Classifier: Operating System :: OS Independent
Requires-Python: >=3.7
License-File: LICENSE
Requires-Dist: slideflow >=3.0
Requires-Dist: numpy
Requires-Dist: pillow >=6.0.0
Requires-Dist: gdown
Requires-Dist: torch
Requires-Dist: torchvision
Requires-Dist: timm
Requires-Dist: huggingface-hub
Requires-Dist: transformers
Requires-Dist: fastai
Requires-Dist: scikit-misc
Provides-Extra: gigapath
Requires-Dist: timm >=1.0.3 ; extra == 'gigapath'
Requires-Dist: fairscale ; extra == 'gigapath'
Requires-Dist: flash-attn ==2.5.8 ; extra == 'gigapath'
Requires-Dist: einops ; extra == 'gigapath'
